[
  {
    "id": "1750863789314mwm9e",
    "status": "pending",
    "appID": "C:\\Users\\Administrator\\OneDrive - Diagonal Consulting LLP\\Documents\\Qlik\\Sense\\Apps\\BikeShare.qvf",
    "appName": "BikeShare",
    "vOriginSpaceName": "Development",
    "vTargetSpaceName": "UAT",
    "vProposer": "Vighnesh Gawad",
    "vReviewer": "Vighnesh Gawad",
    "sheetName": "User Demographics and Trip Behaviour",
    "vObjectId": "kgp",
    "feedback": "change this",
    "feedbackCreatedAt": "6/25/2025, 8:33:09 PM",
    "lastUpdatedAt": "6/25/2025, 8:33:09 PM",
    "responses": []
  }
]