[
  {
    "id": "1750321241233wovhp",
    "status": "pending",
    "appID": "C:\\Users\\vighn\\OneDrive\\Documents\\Qlik\\Sense\\Apps\\test_app_for_workflow.qvf",
    "appName": "test_app_for_workflow",
    "vOriginSpaceName": "personal",
    "vTargetSpaceName": "Sales Prod",
    "vProposer": "Vighnesh Gawad",
    "vReviewer": "Vighnesh Gawad",
    "sheetName": "My new sheet (1) (1)",
    "vObjectId": "ee314826-4179-4ae7-97ed-b43e8ca5dd6b",
    "feedback": "this is feedback",
    "feedbackCreatedAt": "19/6/2025, 1:50:41 pm",
    "lastUpdatedAt": "19/6/2025, 1:50:41 pm",
    "responses": []
  }
]