[
  {
    "id": "1749122591667jjfkj",
    "status": "pending",
    "appID": "dded1e50-0d4a-48c0-8dbe-14112e3b7786",
    "appName": "E-Com Dashboard",
    "vOriginSpaceName": "personal",
    "vTargetSpaceName": "Sales Prod",
    "vProposer": "Vighnesh Gawad",
    "vReviewer": "Vighnesh Gawad",
    "sheetName": "Home Page",
    "vObjectId": "jSaSL",
    "feedback": "this is",
    "feedbackCreatedAt": "5/6/2025, 4:53:11 pm"
  },
  {
    "id": "1749122604747q33ru",
    "status": "pending",
    "appID": "dded1e50-0d4a-48c0-8dbe-14112e3b7786",
    "appName": "E-Com Dashboard",
    "vOriginSpaceName": "personal",
    "vTargetSpaceName": "Sales Prod",
    "vProposer": "Vighnesh Gawad",
    "vReviewer": "Vighnesh Gawad",
    "sheetName": "Home Page",
    "vObjectId": "jumCEz",
    "feedback": "this",
    "feedbackCreatedAt": "5/6/2025, 4:53:24 pm"
  }
]